spreadpandas/__init__.py
spreadpandas/custom_types.py
spreadpandas/operations.py
spreadpandas/spreadsheet.py
spreadpandas/spreadsheet_element.py
spreadpandas-0.0.2.dist-info/LICENSE
spreadpandas-0.0.2.dist-info/METADATA
spreadpandas-0.0.2.dist-info/WHEEL
spreadpandas-0.0.2.dist-info/top_level.txt
spreadpandas-0.0.2.dist-info/RECORD
