Metadata-Version: 2.1
Name: spreadpandas
Version: 0.0.2
Summary: Get the spreadsheet representation of a pandas data frame.
Home-page: https://github.com/FilippoPisello/SpreadPandas
Author: Filippo Pisello
Author-email: filippo.pisello@live.it
License: MIT
Platform: UNKNOWN
Classifier: License :: OSI Approved :: MIT License
Classifier: Programming Language :: Python :: 3
Classifier: Programming Language :: Python :: 3.7
Classifier: Programming Language :: Python :: 3.8
Classifier: Programming Language :: Python :: 3.9
Classifier: Programming Language :: Python :: 3.10
Classifier: Operating System :: OS Independent
Requires-Python: >=3.7
License-File: LICENSE
Requires-Dist: numpy (>=1.10)
Requires-Dist: pandas (>=1.1.0)
